{
	"name": "AASSupplyRefresh",
	"properties": {
		"activities": [
			{
				"name": "RefreshNightlyFacts",
				"type": "WebActivity",
				"dependsOn": [],
				"policy": {
					"timeout": "7.00:00:00",
					"retry": 0,
					"retryIntervalInSeconds": 30,
					"secureOutput": false,
					"secureInput": false
				},
				"userProperties": [],
				"typeProperties": {
					"url": "https://northcentralus.asazure.windows.net/servers/carharttbiasq01/models/Supply/refreshes",
					"method": "POST",
					"body": {
						"value": "@concat('{\n    \"Type\": \"Full\",\n    \"CommitMode\": \"transactional\",\n    \"MaxParallelism\": 4,\n    \"RetryCount\": 2,\n    \"Objects\": [\n        {\n            \"table\": \"Production Plans\",\n            \"partition\": \"Production Plans - Nightly\"\n        },\n        {\n            \"table\": \"Inventory Plans\",\n            \"partition\": \"NightlyPartition\"\n        },\n        {\n            \"table\": \"Dates\"\n        }\n    ]\n}')",
						"type": "Expression"
					},
					"authentication": {
						"type": "MSI",
						"resource": "https://*.asazure.windows.net  "
					}
				}
			}
		],
		"annotations": []
	}
}